likepy/__init__.py
likepy/exceptions.py
likepy/helpers.py
likepy/restricted.py
likepy/restricted_builtins.py
likepy/transformer.py
likepy-0.3.0.dist-info/LICENSE
likepy-0.3.0.dist-info/METADATA
likepy-0.3.0.dist-info/WHEEL
likepy-0.3.0.dist-info/top_level.txt
likepy-0.3.0.dist-info/RECORD
