Metadata-Version: 2.1
Name: likepy
Version: 0.3.0
Summary: Provoide a trust environment for python like programming language, like RestrictedPython. 
Home-page: https://github.com/zeaphoo/likepy
Author: Zhuo Wei
Author-email: zeaphoo@qq.com
License: MIT License
Keywords: restricted
Classifier: Development Status :: 4 - Beta
Classifier: License :: OSI Approved :: MIT License
Classifier: Programming Language :: Python
Classifier: Operating System :: OS Independent
Classifier: Programming Language :: Python :: 3
Classifier: Programming Language :: Python :: 3.6
Classifier: Programming Language :: Python :: 3.7
Classifier: Programming Language :: Python :: 3.8
Classifier: Programming Language :: Python :: 3.9
Classifier: Programming Language :: Python :: 3.10
Classifier: Programming Language :: Python :: Implementation :: CPython
Requires-Python: >=3.6, <3.12
License-File: LICENSE
Provides-Extra: test
Requires-Dist: pytest ; extra == 'test'
Requires-Dist: pytest-mock ; extra == 'test'
